bipedal/__init__.py
bipedal/bipedal.py
bipedal-0.0.1.dist-info/LICENSE
bipedal-0.0.1.dist-info/METADATA
bipedal-0.0.1.dist-info/WHEEL
bipedal-0.0.1.dist-info/top_level.txt
bipedal-0.0.1.dist-info/RECORD
