Metadata-Version: 2.1
Name: bipedal
Version: 0.0.1
Summary: Bioinformatics Pipelines for Experimental Data Analysis
License-File: LICENSE
